devops_agent/__init__.py
devops_agent/cli.py
devops_agent/core/__init__.py
devops_agent/core/master_agent.py
devops_agent/database/__init__.py
devops_agent/database/db_architect.py
devops_agent/database/db_optimizer.py
devops_agent/database/sql_pro.py
devops_agent/devops/__init__.py
devops_agent/devops/devops_agent.py
devops_agent/k8s/__init__.py
devops_agent/k8s/kubernetes_agent.py
devops_agent/loganalytics/__init__.py
devops_agent/loganalytics/log_analysis_agent.py
devops_agent/prompts/__init__.py
devops_agent/prompts/db_architect.poml
devops_agent/prompts/db_optimizer.poml
devops_agent/prompts/db_sql_pro.poml
devops_agent/prompts/devops.poml
devops_agent/prompts/kubernetes.poml
devops_agent/prompts/terraform.poml
devops_agent/templates/__init__.py
devops_agent/terraform/__init__.py
devops_agent/terraform/terraform_agent.py
devops_agent/utils/__init__.py
devops_agent/utils/model_provider.py
devops_agent/utils/prompt_generator_from_poml.py
devops_agent/utils/stream_handler.py
devops_agent-0.0.6.dist-info/licenses/LICENSE
devops_agent-0.0.6.dist-info/METADATA
devops_agent-0.0.6.dist-info/WHEEL
devops_agent-0.0.6.dist-info/entry_points.txt
devops_agent-0.0.6.dist-info/top_level.txt
devops_agent-0.0.6.dist-info/RECORD
