Metadata-Version: 2.4
Name: devops-agent
Version: 0.0.6
Summary: AI-powered DevOps CLI assistant
Home-page: https://github.com/yourusername/devops-agent
Author: Your Name
Author-email: M K Pavan Kumar <manthapavankumar11@gamil.com>
License: MIT
Keywords: devops,cli,ai,automation,terraform,kubernetes,docker
Classifier: Development Status :: 3 - Alpha
Classifier: Intended Audience :: Developers
Classifier: Topic :: Software Development :: Build Tools
Classifier: License :: OSI Approved :: Apache Software License
Classifier: Programming Language :: Python :: 3
Requires-Python: >=3.8
License-File: LICENSE
Requires-Dist: click>=8.3.1
Requires-Dist: rich>=14.2.0
Requires-Dist: anthropic>=0.75.0
Requires-Dist: openai>=2.14.0
Requires-Dist: google-genai>=1.56.0
Requires-Dist: pyyaml>=6.0.3
Requires-Dist: python-dotenv>=1.2.1
Requires-Dist: requests>=2.32.5
Requires-Dist: colorama>=0.4.6
Requires-Dist: agno>=2.3.21
Requires-Dist: poml>=0.0.8
Requires-Dist: qdrant-client>=1.16.2
Requires-Dist: fastembed>=0.7.4
Requires-Dist: ddgs>=9.10.0
Requires-Dist: sqlalchemy>=2.0.45
Requires-Dist: chromadb>=1.4.0
Requires-Dist: ollama>=0.6.1
Provides-Extra: dev
Requires-Dist: black>=25.12.0; extra == "dev"
Requires-Dist: isort>=7.0.0; extra == "dev"
Requires-Dist: flake8>=7.3.0; extra == "dev"
Dynamic: author
Dynamic: home-page
Dynamic: license-file
Dynamic: requires-python
